{"frames": {

"crab.png":
{
	"frame": {"x":248,"y":579,"w":22,"h":24},
	"rotated": false,
	"trimmed": false,
	"spriteSourceSize": {"x":0,"y":0,"w":22,"h":24},
	"sourceSize": {"w":22,"h":24}
},
"fire_burning_0001.png":
{
	"frame": {"x":428,"y":250,"w":46,"h":61},
	"rotated": false,
	"trimmed": true,
	"spriteSourceSize": {"x":3,"y":12,"w":46,"h":61},
	"sourceSize": {"w":53,"h":74}
},
"fire_burning_0002.png":
{
	"frame": {"x":476,"y":251,"w":46,"h":61},
	"rotated": false,
	"trimmed": true,
	"spriteSourceSize": {"x":3,"y":12,"w":46,"h":61},
	"sourceSize": {"w":53,"h":74}
},
"fire_burning_0003.png":
{
	"frame": {"x":524,"y":251,"w":46,"h":61},
	"rotated": false,
	"trimmed": true,
	"spriteSourceSize": {"x":3,"y":12,"w":46,"h":61},
	"sourceSize": {"w":53,"h":74}
},
"fire_pit_.png":
{
	"frame": {"x":276,"y":550,"w":47,"h":28},
	"rotated": false,
	"trimmed": true,
	"spriteSourceSize": {"x":3,"y":43,"w":47,"h":28},
	"sourceSize": {"w":53,"h":74}
},
"fire_wood_.png":
{
	"frame": {"x":506,"y":146,"w":47,"h":29},
	"rotated": false,
	"trimmed": true,
	"spriteSourceSize": {"x":3,"y":44,"w":47,"h":29},
	"sourceSize": {"w":53,"h":74}
},
"flintsteel.png":
{
	"frame": {"x":204,"y":327,"w":42,"h":27},
	"rotated": false,
	"trimmed": false,
	"spriteSourceSize": {"x":0,"y":0,"w":42,"h":27},
	"sourceSize": {"w":42,"h":27}
},
"log.png":
{
	"frame": {"x":248,"y":548,"w":26,"h":29},
	"rotated": false,
	"trimmed": false,
	"spriteSourceSize": {"x":0,"y":0,"w":26,"h":29},
	"sourceSize": {"w":26,"h":29}
},
"movingPerson1_die0001.png":
{
	"frame": {"x":67,"y":313,"w":37,"h":70},
	"rotated": false,
	"trimmed": true,
	"spriteSourceSize": {"x":22,"y":8,"w":37,"h":70},
	"sourceSize": {"w":81,"h":79}
},
"movingPerson1_die0002.png":
{
	"frame": {"x":495,"y":177,"w":36,"h":72},
	"rotated": false,
	"trimmed": true,
	"spriteSourceSize": {"x":22,"y":6,"w":36,"h":72},
	"sourceSize": {"w":81,"h":79}
},
"movingPerson1_die0003.png":
{
	"frame": {"x":100,"y":210,"w":59,"h":73},
	"rotated": false,
	"trimmed": true,
	"spriteSourceSize": {"x":10,"y":1,"w":59,"h":73},
	"sourceSize": {"w":81,"h":79}
},
"movingPerson1_die0004.png":
{
	"frame": {"x":307,"y":105,"w":66,"h":63},
	"rotated": false,
	"trimmed": true,
	"spriteSourceSize": {"x":7,"y":9,"w":66,"h":63},
	"sourceSize": {"w":81,"h":79}
},
"movingPerson1_die0005.png":
{
	"frame": {"x":107,"y":360,"w":71,"h":53},
	"rotated": false,
	"trimmed": true,
	"spriteSourceSize": {"x":5,"y":23,"w":71,"h":53},
	"sourceSize": {"w":81,"h":79}
},
"movingPerson1_die0006.png":
{
	"frame": {"x":185,"y":415,"w":73,"h":38},
	"rotated": false,
	"trimmed": true,
	"spriteSourceSize": {"x":6,"y":37,"w":73,"h":38},
	"sourceSize": {"w":81,"h":79}
},
"movingPerson1_die0007.png":
{
	"frame": {"x":260,"y":403,"w":71,"h":37},
	"rotated": false,
	"trimmed": true,
	"spriteSourceSize": {"x":5,"y":40,"w":71,"h":37},
	"sourceSize": {"w":81,"h":79}
},
"movingPerson1_hurt0001.png":
{
	"frame": {"x":301,"y":331,"w":37,"h":70},
	"rotated": false,
	"trimmed": true,
	"spriteSourceSize": {"x":9,"y":8,"w":37,"h":70},
	"sourceSize": {"w":54,"h":79}
},
"movingPerson1_hurt0002.png":
{
	"frame": {"x":533,"y":177,"w":36,"h":72},
	"rotated": false,
	"trimmed": true,
	"spriteSourceSize": {"x":8,"y":6,"w":36,"h":72},
	"sourceSize": {"w":54,"h":79}
},
"movingPerson1_hurt0003.png":
{
	"frame": {"x":564,"y":2,"w":39,"h":74},
	"rotated": false,
	"trimmed": true,
	"spriteSourceSize": {"x":4,"y":4,"w":39,"h":74},
	"sourceSize": {"w":54,"h":79}
},
"movingPerson1_hurt0004.png":
{
	"frame": {"x":161,"y":210,"w":39,"h":74},
	"rotated": false,
	"trimmed": true,
	"spriteSourceSize": {"x":4,"y":4,"w":39,"h":74},
	"sourceSize": {"w":54,"h":79}
},
"movingPerson1_hurt0005.png":
{
	"frame": {"x":409,"y":165,"w":35,"h":72},
	"rotated": false,
	"trimmed": true,
	"spriteSourceSize": {"x":9,"y":6,"w":35,"h":72},
	"sourceSize": {"w":54,"h":79}
},
"movingPerson1_hurt0006.png":
{
	"frame": {"x":301,"y":331,"w":37,"h":70},
	"rotated": false,
	"trimmed": true,
	"spriteSourceSize": {"x":9,"y":8,"w":37,"h":70},
	"sourceSize": {"w":54,"h":79}
},
"movingPerson1_hurt0007.png":
{
	"frame": {"x":301,"y":331,"w":37,"h":70},
	"rotated": false,
	"trimmed": true,
	"spriteSourceSize": {"x":9,"y":8,"w":37,"h":70},
	"sourceSize": {"w":54,"h":79}
},
"movingPerson1_idle0001.png":
{
	"frame": {"x":462,"y":388,"w":36,"h":70},
	"rotated": false,
	"trimmed": true,
	"spriteSourceSize": {"x":6,"y":8,"w":36,"h":70},
	"sourceSize": {"w":46,"h":79}
},
"movingPerson1_idle0002.png":
{
	"frame": {"x":462,"y":388,"w":36,"h":70},
	"rotated": false,
	"trimmed": true,
	"spriteSourceSize": {"x":6,"y":8,"w":36,"h":70},
	"sourceSize": {"w":46,"h":79}
},
"movingPerson1_shoot0001.png":
{
	"frame": {"x":374,"y":460,"w":37,"h":70},
	"rotated": false,
	"trimmed": true,
	"spriteSourceSize": {"x":5,"y":8,"w":37,"h":70},
	"sourceSize": {"w":64,"h":79}
},
"movingPerson1_shoot0002.png":
{
	"frame": {"x":446,"y":105,"w":58,"h":70},
	"rotated": false,
	"trimmed": true,
	"spriteSourceSize": {"x":5,"y":8,"w":58,"h":70},
	"sourceSize": {"w":64,"h":79}
},
"movingPerson1_shoot0003.png":
{
	"frame": {"x":2,"y":535,"w":59,"h":70},
	"rotated": false,
	"trimmed": true,
	"spriteSourceSize": {"x":5,"y":8,"w":59,"h":70},
	"sourceSize": {"w":64,"h":79}
},
"movingPerson1_shoot0004.png":
{
	"frame": {"x":63,"y":535,"w":56,"h":70},
	"rotated": false,
	"trimmed": true,
	"spriteSourceSize": {"x":5,"y":8,"w":56,"h":70},
	"sourceSize": {"w":64,"h":79}
},
"movingPerson1_shoot0005.png":
{
	"frame": {"x":63,"y":535,"w":56,"h":70},
	"rotated": false,
	"trimmed": true,
	"spriteSourceSize": {"x":5,"y":8,"w":56,"h":70},
	"sourceSize": {"w":64,"h":79}
},
"movingPerson1_shoot0006.png":
{
	"frame": {"x":63,"y":535,"w":56,"h":70},
	"rotated": false,
	"trimmed": true,
	"spriteSourceSize": {"x":5,"y":8,"w":56,"h":70},
	"sourceSize": {"w":64,"h":79}
},
"movingPerson1_shoot0007.png":
{
	"frame": {"x":63,"y":535,"w":56,"h":70},
	"rotated": false,
	"trimmed": true,
	"spriteSourceSize": {"x":5,"y":8,"w":56,"h":70},
	"sourceSize": {"w":64,"h":79}
},
"movingPerson1_use0001.png":
{
	"frame": {"x":295,"y":478,"w":38,"h":70},
	"rotated": false,
	"trimmed": true,
	"spriteSourceSize": {"x":5,"y":8,"w":38,"h":70},
	"sourceSize": {"w":54,"h":79}
},
"movingPerson1_use0002.png":
{
	"frame": {"x":262,"y":182,"w":46,"h":71},
	"rotated": false,
	"trimmed": true,
	"spriteSourceSize": {"x":7,"y":7,"w":46,"h":71},
	"sourceSize": {"w":54,"h":79}
},
"movingPerson1_use0003.png":
{
	"frame": {"x":155,"y":286,"w":47,"h":72},
	"rotated": false,
	"trimmed": true,
	"spriteSourceSize": {"x":7,"y":6,"w":47,"h":72},
	"sourceSize": {"w":54,"h":79}
},
"movingPerson1_use0004.png":
{
	"frame": {"x":252,"y":255,"w":47,"h":71},
	"rotated": false,
	"trimmed": true,
	"spriteSourceSize": {"x":7,"y":7,"w":47,"h":71},
	"sourceSize": {"w":54,"h":79}
},
"movingPerson1_use0005.png":
{
	"frame": {"x":381,"y":313,"w":47,"h":71},
	"rotated": false,
	"trimmed": true,
	"spriteSourceSize": {"x":7,"y":7,"w":47,"h":71},
	"sourceSize": {"w":54,"h":79}
},
"movingPerson1_use0006.png":
{
	"frame": {"x":259,"y":107,"w":46,"h":73},
	"rotated": false,
	"trimmed": true,
	"spriteSourceSize": {"x":7,"y":5,"w":46,"h":73},
	"sourceSize": {"w":54,"h":79}
},
"movingPerson1_use0007.png":
{
	"frame": {"x":563,"y":78,"w":40,"h":72},
	"rotated": false,
	"trimmed": true,
	"spriteSourceSize": {"x":7,"y":6,"w":40,"h":72},
	"sourceSize": {"w":54,"h":79}
},
"movingPerson1_walk0001.png":
{
	"frame": {"x":423,"y":388,"w":37,"h":70},
	"rotated": false,
	"trimmed": true,
	"spriteSourceSize": {"x":5,"y":8,"w":37,"h":70},
	"sourceSize": {"w":46,"h":79}
},
"movingPerson1_walk0002.png":
{
	"frame": {"x":522,"y":314,"w":45,"h":68},
	"rotated": false,
	"trimmed": true,
	"spriteSourceSize": {"x":0,"y":7,"w":45,"h":68},
	"sourceSize": {"w":46,"h":79}
},
"movingPerson1_walk0003.png":
{
	"frame": {"x":423,"y":388,"w":37,"h":70},
	"rotated": false,
	"trimmed": true,
	"spriteSourceSize": {"x":5,"y":8,"w":37,"h":70},
	"sourceSize": {"w":46,"h":79}
},
"movingPerson1_walk0004.png":
{
	"frame": {"x":569,"y":314,"w":36,"h":71},
	"rotated": false,
	"trimmed": true,
	"spriteSourceSize": {"x":7,"y":7,"w":36,"h":71},
	"sourceSize": {"w":46,"h":79}
},
"movingPerson2_die0001.png":
{
	"frame": {"x":170,"y":511,"w":35,"h":73},
	"rotated": false,
	"trimmed": true,
	"spriteSourceSize": {"x":22,"y":5,"w":35,"h":73},
	"sourceSize": {"w":81,"h":79}
},
"movingPerson2_die0002.png":
{
	"frame": {"x":335,"y":460,"w":37,"h":72},
	"rotated": false,
	"trimmed": true,
	"spriteSourceSize": {"x":20,"y":6,"w":37,"h":72},
	"sourceSize": {"w":81,"h":79}
},
"movingPerson2_die0003.png":
{
	"frame": {"x":2,"y":313,"w":63,"h":70},
	"rotated": false,
	"trimmed": true,
	"spriteSourceSize": {"x":6,"y":4,"w":63,"h":70},
	"sourceSize": {"w":81,"h":79}
},
"movingPerson2_die0004.png":
{
	"frame": {"x":375,"y":105,"w":69,"h":58},
	"rotated": false,
	"trimmed": true,
	"spriteSourceSize": {"x":4,"y":14,"w":69,"h":58},
	"sourceSize": {"w":81,"h":79}
},
"movingPerson2_die0005.png":
{
	"frame": {"x":108,"y":457,"w":72,"h":52},
	"rotated": false,
	"trimmed": true,
	"spriteSourceSize": {"x":4,"y":23,"w":72,"h":52},
	"sourceSize": {"w":81,"h":79}
},
"movingPerson2_die0006.png":
{
	"frame": {"x":107,"y":415,"w":76,"h":40},
	"rotated": false,
	"trimmed": true,
	"spriteSourceSize": {"x":3,"y":37,"w":76,"h":40},
	"sourceSize": {"w":81,"h":79}
},
"movingPerson2_die0007.png":
{
	"frame": {"x":260,"y":442,"w":73,"h":34},
	"rotated": false,
	"trimmed": true,
	"spriteSourceSize": {"x":3,"y":43,"w":73,"h":34},
	"sourceSize": {"w":81,"h":79}
},
"movingPerson2_hurt0001.png":
{
	"frame": {"x":452,"y":460,"w":35,"h":73},
	"rotated": false,
	"trimmed": true,
	"spriteSourceSize": {"x":9,"y":5,"w":35,"h":73},
	"sourceSize": {"w":54,"h":79}
},
"movingPerson2_hurt0002.png":
{
	"frame": {"x":301,"y":255,"w":37,"h":74},
	"rotated": false,
	"trimmed": true,
	"spriteSourceSize": {"x":6,"y":4,"w":37,"h":74},
	"sourceSize": {"w":54,"h":79}
},
"movingPerson2_hurt0003.png":
{
	"frame": {"x":62,"y":385,"w":43,"h":73},
	"rotated": false,
	"trimmed": true,
	"spriteSourceSize": {"x":0,"y":5,"w":43,"h":73},
	"sourceSize": {"w":54,"h":79}
},
"movingPerson2_hurt0004.png":
{
	"frame": {"x":430,"y":313,"w":43,"h":73},
	"rotated": false,
	"trimmed": true,
	"spriteSourceSize": {"x":0,"y":5,"w":43,"h":73},
	"sourceSize": {"w":54,"h":79}
},
"movingPerson2_hurt0005.png":
{
	"frame": {"x":340,"y":239,"w":37,"h":74},
	"rotated": false,
	"trimmed": true,
	"spriteSourceSize": {"x":6,"y":4,"w":37,"h":74},
	"sourceSize": {"w":54,"h":79}
},
"movingPerson2_hurt0006.png":
{
	"frame": {"x":452,"y":460,"w":35,"h":73},
	"rotated": false,
	"trimmed": true,
	"spriteSourceSize": {"x":9,"y":5,"w":35,"h":73},
	"sourceSize": {"w":54,"h":79}
},
"movingPerson2_hurt0007.png":
{
	"frame": {"x":452,"y":460,"w":35,"h":73},
	"rotated": false,
	"trimmed": true,
	"spriteSourceSize": {"x":9,"y":5,"w":35,"h":73},
	"sourceSize": {"w":54,"h":79}
},
"movingPerson2_idle0001.png":
{
	"frame": {"x":500,"y":386,"w":35,"h":73},
	"rotated": false,
	"trimmed": true,
	"spriteSourceSize": {"x":5,"y":5,"w":35,"h":73},
	"sourceSize": {"w":46,"h":79}
},
"movingPerson2_idle0002.png":
{
	"frame": {"x":500,"y":386,"w":35,"h":73},
	"rotated": false,
	"trimmed": true,
	"spriteSourceSize": {"x":5,"y":5,"w":35,"h":73},
	"sourceSize": {"w":46,"h":79}
},
"movingPerson2_shoot0001.png":
{
	"frame": {"x":489,"y":461,"w":35,"h":73},
	"rotated": false,
	"trimmed": true,
	"spriteSourceSize": {"x":5,"y":5,"w":35,"h":73},
	"sourceSize": {"w":64,"h":79}
},
"movingPerson2_shoot0002.png":
{
	"frame": {"x":2,"y":385,"w":58,"h":73},
	"rotated": false,
	"trimmed": true,
	"spriteSourceSize": {"x":5,"y":5,"w":58,"h":73},
	"sourceSize": {"w":64,"h":79}
},
"movingPerson2_shoot0003.png":
{
	"frame": {"x":198,"y":107,"w":59,"h":73},
	"rotated": false,
	"trimmed": true,
	"spriteSourceSize": {"x":5,"y":5,"w":59,"h":73},
	"sourceSize": {"w":64,"h":79}
},
"movingPerson2_shoot0004.png":
{
	"frame": {"x":2,"y":460,"w":56,"h":73},
	"rotated": false,
	"trimmed": true,
	"spriteSourceSize": {"x":5,"y":5,"w":56,"h":73},
	"sourceSize": {"w":64,"h":79}
},
"movingPerson2_shoot0005.png":
{
	"frame": {"x":2,"y":460,"w":56,"h":73},
	"rotated": false,
	"trimmed": true,
	"spriteSourceSize": {"x":5,"y":5,"w":56,"h":73},
	"sourceSize": {"w":64,"h":79}
},
"movingPerson2_shoot0006.png":
{
	"frame": {"x":2,"y":460,"w":56,"h":73},
	"rotated": false,
	"trimmed": true,
	"spriteSourceSize": {"x":5,"y":5,"w":56,"h":73},
	"sourceSize": {"w":64,"h":79}
},
"movingPerson2_shoot0007.png":
{
	"frame": {"x":2,"y":460,"w":56,"h":73},
	"rotated": false,
	"trimmed": true,
	"spriteSourceSize": {"x":5,"y":5,"w":56,"h":73},
	"sourceSize": {"w":64,"h":79}
},
"movingPerson2_use0001.png":
{
	"frame": {"x":526,"y":461,"w":35,"h":73},
	"rotated": false,
	"trimmed": true,
	"spriteSourceSize": {"x":5,"y":5,"w":35,"h":73},
	"sourceSize": {"w":54,"h":79}
},
"movingPerson2_use0002.png":
{
	"frame": {"x":60,"y":460,"w":46,"h":73},
	"rotated": false,
	"trimmed": true,
	"spriteSourceSize": {"x":7,"y":5,"w":46,"h":73},
	"sourceSize": {"w":54,"h":79}
},
"movingPerson2_use0003.png":
{
	"frame": {"x":253,"y":328,"w":46,"h":73},
	"rotated": false,
	"trimmed": true,
	"spriteSourceSize": {"x":8,"y":5,"w":46,"h":73},
	"sourceSize": {"w":54,"h":79}
},
"movingPerson2_use0004.png":
{
	"frame": {"x":106,"y":285,"w":47,"h":73},
	"rotated": false,
	"trimmed": true,
	"spriteSourceSize": {"x":7,"y":5,"w":47,"h":73},
	"sourceSize": {"w":54,"h":79}
},
"movingPerson2_use0005.png":
{
	"frame": {"x":121,"y":511,"w":47,"h":73},
	"rotated": false,
	"trimmed": true,
	"spriteSourceSize": {"x":7,"y":5,"w":47,"h":73},
	"sourceSize": {"w":54,"h":79}
},
"movingPerson2_use0006.png":
{
	"frame": {"x":204,"y":251,"w":46,"h":74},
	"rotated": false,
	"trimmed": true,
	"spriteSourceSize": {"x":7,"y":4,"w":46,"h":74},
	"sourceSize": {"w":54,"h":79}
},
"movingPerson2_use0007.png":
{
	"frame": {"x":207,"y":531,"w":39,"h":73},
	"rotated": false,
	"trimmed": true,
	"spriteSourceSize": {"x":8,"y":5,"w":39,"h":73},
	"sourceSize": {"w":54,"h":79}
},
"movingPerson2_walk0001.png":
{
	"frame": {"x":500,"y":386,"w":35,"h":73},
	"rotated": false,
	"trimmed": true,
	"spriteSourceSize": {"x":5,"y":5,"w":35,"h":73},
	"sourceSize": {"w":46,"h":79}
},
"movingPerson2_walk0002.png":
{
	"frame": {"x":475,"y":314,"w":45,"h":70},
	"rotated": false,
	"trimmed": true,
	"spriteSourceSize": {"x":0,"y":5,"w":45,"h":70},
	"sourceSize": {"w":46,"h":79}
},
"movingPerson2_walk0003.png":
{
	"frame": {"x":500,"y":386,"w":35,"h":73},
	"rotated": false,
	"trimmed": true,
	"spriteSourceSize": {"x":5,"y":5,"w":35,"h":73},
	"sourceSize": {"w":46,"h":79}
},
"movingPerson2_walk0004.png":
{
	"frame": {"x":572,"y":152,"w":33,"h":73},
	"rotated": false,
	"trimmed": true,
	"spriteSourceSize": {"x":7,"y":5,"w":33,"h":73},
	"sourceSize": {"w":46,"h":79}
},
"movingPerson3_die0001.png":
{
	"frame": {"x":369,"y":170,"w":38,"h":67},
	"rotated": false,
	"trimmed": true,
	"spriteSourceSize": {"x":22,"y":11,"w":38,"h":67},
	"sourceSize": {"w":81,"h":79}
},
"movingPerson3_die0002.png":
{
	"frame": {"x":495,"y":177,"w":36,"h":72},
	"rotated": false,
	"trimmed": true,
	"spriteSourceSize": {"x":22,"y":6,"w":36,"h":72},
	"sourceSize": {"w":81,"h":79}
},
"movingPerson3_die0003.png":
{
	"frame": {"x":503,"y":2,"w":59,"h":73},
	"rotated": false,
	"trimmed": true,
	"spriteSourceSize": {"x":10,"y":1,"w":59,"h":73},
	"sourceSize": {"w":81,"h":79}
},
"movingPerson3_die0004.png":
{
	"frame": {"x":307,"y":105,"w":66,"h":63},
	"rotated": false,
	"trimmed": true,
	"spriteSourceSize": {"x":7,"y":9,"w":66,"h":63},
	"sourceSize": {"w":81,"h":79}
},
"movingPerson3_die0005.png":
{
	"frame": {"x":180,"y":360,"w":71,"h":53},
	"rotated": false,
	"trimmed": true,
	"spriteSourceSize": {"x":5,"y":23,"w":71,"h":53},
	"sourceSize": {"w":81,"h":79}
},
"movingPerson3_die0006.png":
{
	"frame": {"x":185,"y":415,"w":73,"h":38},
	"rotated": false,
	"trimmed": true,
	"spriteSourceSize": {"x":6,"y":37,"w":73,"h":38},
	"sourceSize": {"w":81,"h":79}
},
"movingPerson3_die0007.png":
{
	"frame": {"x":260,"y":403,"w":71,"h":37},
	"rotated": false,
	"trimmed": true,
	"spriteSourceSize": {"x":5,"y":40,"w":71,"h":37},
	"sourceSize": {"w":81,"h":79}
},
"movingPerson3_hurt0001.png":
{
	"frame": {"x":537,"y":387,"w":38,"h":67},
	"rotated": false,
	"trimmed": true,
	"spriteSourceSize": {"x":9,"y":11,"w":38,"h":67},
	"sourceSize": {"w":54,"h":79}
},
"movingPerson3_hurt0002.png":
{
	"frame": {"x":533,"y":177,"w":36,"h":72},
	"rotated": false,
	"trimmed": true,
	"spriteSourceSize": {"x":8,"y":6,"w":36,"h":72},
	"sourceSize": {"w":54,"h":79}
},
"movingPerson3_hurt0003.png":
{
	"frame": {"x":340,"y":315,"w":39,"h":74},
	"rotated": false,
	"trimmed": true,
	"spriteSourceSize": {"x":4,"y":4,"w":39,"h":74},
	"sourceSize": {"w":54,"h":79}
},
"movingPerson3_hurt0004.png":
{
	"frame": {"x":207,"y":455,"w":39,"h":74},
	"rotated": false,
	"trimmed": true,
	"spriteSourceSize": {"x":4,"y":4,"w":39,"h":74},
	"sourceSize": {"w":54,"h":79}
},
"movingPerson3_hurt0005.png":
{
	"frame": {"x":409,"y":165,"w":35,"h":72},
	"rotated": false,
	"trimmed": true,
	"spriteSourceSize": {"x":9,"y":6,"w":35,"h":72},
	"sourceSize": {"w":54,"h":79}
},
"movingPerson3_hurt0006.png":
{
	"frame": {"x":301,"y":331,"w":37,"h":70},
	"rotated": false,
	"trimmed": true,
	"spriteSourceSize": {"x":9,"y":8,"w":37,"h":70},
	"sourceSize": {"w":54,"h":79}
},
"movingPerson3_hurt0007.png":
{
	"frame": {"x":301,"y":331,"w":37,"h":70},
	"rotated": false,
	"trimmed": true,
	"spriteSourceSize": {"x":9,"y":8,"w":37,"h":70},
	"sourceSize": {"w":54,"h":79}
},
"movingPerson3_idle0001.png":
{
	"frame": {"x":563,"y":456,"w":38,"h":67},
	"rotated": false,
	"trimmed": true,
	"spriteSourceSize": {"x":5,"y":11,"w":38,"h":67},
	"sourceSize": {"w":46,"h":79}
},
"movingPerson3_idle0002.png":
{
	"frame": {"x":563,"y":456,"w":38,"h":67},
	"rotated": false,
	"trimmed": true,
	"spriteSourceSize": {"x":5,"y":11,"w":38,"h":67},
	"sourceSize": {"w":46,"h":79}
},
"movingPerson3_shoot0001.png":
{
	"frame": {"x":373,"y":534,"w":38,"h":67},
	"rotated": false,
	"trimmed": true,
	"spriteSourceSize": {"x":6,"y":11,"w":38,"h":67},
	"sourceSize": {"w":64,"h":79}
},
"movingPerson3_shoot0002.png":
{
	"frame": {"x":310,"y":170,"w":57,"h":67},
	"rotated": false,
	"trimmed": true,
	"spriteSourceSize": {"x":6,"y":11,"w":57,"h":67},
	"sourceSize": {"w":64,"h":79}
},
"movingPerson3_shoot0003.png":
{
	"frame": {"x":202,"y":182,"w":58,"h":67},
	"rotated": false,
	"trimmed": true,
	"spriteSourceSize": {"x":6,"y":11,"w":58,"h":67},
	"sourceSize": {"w":64,"h":79}
},
"movingPerson3_shoot0004.png":
{
	"frame": {"x":506,"y":77,"w":55,"h":67},
	"rotated": false,
	"trimmed": true,
	"spriteSourceSize": {"x":6,"y":11,"w":55,"h":67},
	"sourceSize": {"w":64,"h":79}
},
"movingPerson3_shoot0005.png":
{
	"frame": {"x":506,"y":77,"w":55,"h":67},
	"rotated": false,
	"trimmed": true,
	"spriteSourceSize": {"x":6,"y":11,"w":55,"h":67},
	"sourceSize": {"w":64,"h":79}
},
"movingPerson3_shoot0006.png":
{
	"frame": {"x":506,"y":77,"w":55,"h":67},
	"rotated": false,
	"trimmed": true,
	"spriteSourceSize": {"x":6,"y":11,"w":55,"h":67},
	"sourceSize": {"w":64,"h":79}
},
"movingPerson3_shoot0007.png":
{
	"frame": {"x":506,"y":77,"w":55,"h":67},
	"rotated": false,
	"trimmed": true,
	"spriteSourceSize": {"x":6,"y":11,"w":55,"h":67},
	"sourceSize": {"w":64,"h":79}
},
"movingPerson3_use0001.png":
{
	"frame": {"x":340,"y":391,"w":39,"h":67},
	"rotated": false,
	"trimmed": true,
	"spriteSourceSize": {"x":5,"y":11,"w":39,"h":67},
	"sourceSize": {"w":54,"h":79}
},
"movingPerson3_use0002.png":
{
	"frame": {"x":262,"y":182,"w":46,"h":71},
	"rotated": false,
	"trimmed": true,
	"spriteSourceSize": {"x":7,"y":7,"w":46,"h":71},
	"sourceSize": {"w":54,"h":79}
},
"movingPerson3_use0003.png":
{
	"frame": {"x":379,"y":239,"w":47,"h":72},
	"rotated": false,
	"trimmed": true,
	"spriteSourceSize": {"x":7,"y":6,"w":47,"h":72},
	"sourceSize": {"w":54,"h":79}
},
"movingPerson3_use0004.png":
{
	"frame": {"x":252,"y":255,"w":47,"h":71},
	"rotated": false,
	"trimmed": true,
	"spriteSourceSize": {"x":7,"y":7,"w":47,"h":71},
	"sourceSize": {"w":54,"h":79}
},
"movingPerson3_use0005.png":
{
	"frame": {"x":446,"y":177,"w":47,"h":71},
	"rotated": false,
	"trimmed": true,
	"spriteSourceSize": {"x":7,"y":7,"w":47,"h":71},
	"sourceSize": {"w":54,"h":79}
},
"movingPerson3_use0006.png":
{
	"frame": {"x":259,"y":107,"w":46,"h":73},
	"rotated": false,
	"trimmed": true,
	"spriteSourceSize": {"x":7,"y":5,"w":46,"h":73},
	"sourceSize": {"w":54,"h":79}
},
"movingPerson3_use0007.png":
{
	"frame": {"x":381,"y":386,"w":40,"h":72},
	"rotated": false,
	"trimmed": true,
	"spriteSourceSize": {"x":7,"y":6,"w":40,"h":72},
	"sourceSize": {"w":54,"h":79}
},
"movingPerson3_walk0001.png":
{
	"frame": {"x":563,"y":456,"w":38,"h":67},
	"rotated": false,
	"trimmed": true,
	"spriteSourceSize": {"x":5,"y":11,"w":38,"h":67},
	"sourceSize": {"w":46,"h":79}
},
"movingPerson3_walk0002.png":
{
	"frame": {"x":248,"y":478,"w":45,"h":68},
	"rotated": false,
	"trimmed": true,
	"spriteSourceSize": {"x":0,"y":7,"w":45,"h":68},
	"sourceSize": {"w":46,"h":79}
},
"movingPerson3_walk0003.png":
{
	"frame": {"x":413,"y":460,"w":37,"h":70},
	"rotated": false,
	"trimmed": true,
	"spriteSourceSize": {"x":5,"y":8,"w":37,"h":70},
	"sourceSize": {"w":46,"h":79}
},
"movingPerson3_walk0004.png":
{
	"frame": {"x":335,"y":534,"w":36,"h":71},
	"rotated": false,
	"trimmed": true,
	"spriteSourceSize": {"x":7,"y":7,"w":36,"h":71},
	"sourceSize": {"w":46,"h":79}
},
"portrait0001.png":
{
	"frame": {"x":2,"y":107,"w":96,"h":101},
	"rotated": false,
	"trimmed": true,
	"spriteSourceSize": {"x":1,"y":1,"w":96,"h":101},
	"sourceSize": {"w":97,"h":102}
},
"portrait0002.png":
{
	"frame": {"x":307,"y":2,"w":96,"h":101},
	"rotated": false,
	"trimmed": true,
	"spriteSourceSize": {"x":1,"y":1,"w":96,"h":101},
	"sourceSize": {"w":97,"h":102}
},
"portrait0003.png":
{
	"frame": {"x":2,"y":210,"w":96,"h":101},
	"rotated": false,
	"trimmed": true,
	"spriteSourceSize": {"x":1,"y":1,"w":96,"h":101},
	"sourceSize": {"w":97,"h":102}
},
"portrait0004.png":
{
	"frame": {"x":100,"y":107,"w":96,"h":101},
	"rotated": false,
	"trimmed": true,
	"spriteSourceSize": {"x":1,"y":1,"w":96,"h":101},
	"sourceSize": {"w":97,"h":102}
},
"portrait0005.png":
{
	"frame": {"x":405,"y":2,"w":96,"h":101},
	"rotated": false,
	"trimmed": true,
	"spriteSourceSize": {"x":1,"y":1,"w":96,"h":101},
	"sourceSize": {"w":97,"h":102}
},
"textBox.png":
{
	"frame": {"x":2,"y":2,"w":303,"h":103},
	"rotated": false,
	"trimmed": true,
	"spriteSourceSize": {"x":0,"y":0,"w":303,"h":103},
	"sourceSize": {"w":307,"h":107}
}},
"meta": {
	"app": "http://www.codeandweb.com/texturepacker",
	"version": "1.0",
	"image": "actors.png",
	"format": "RGBA8888",
	"size": {"w":607,"h":607},
	"scale": "1",
	"smartupdate": "$TexturePacker:SmartUpdate:27650333dd4905396e7b41e4b001f185:c27ac83662f18489d1bd7c21edd6045e:dee8eb56aabfb13056c30de9fae0a433$"
}
}
