{
    "maps": {
        "Map1": [
            {
                "height": 5,
                "width": 5,
                "tilesetid": "bottomtiles",
                "data": [
                    3,
                    3,
                    1,
                    1,
                    1,
                    3,
                    3,
                    1,
                    1,
                    1,
                    3,
                    3,
                    3,
                    1,
                    1,
                    3,
                    3,
                    3,
                    1,
                    1,
                    3,
                    3,
                    3,
                    3,
                    3
                ],
                "walkable": [
                    0,
                    0,
                    1,
                    1,
                    1,
                    0,
                    0,
                    1,
                    1,
                    1,
                    0,
                    0,
                    0,
                    1,
                    1,
                    0,
                    0,
                    0,
                    1,
                    1,
                    0,
                    0,
                    0,
                    0,
                    0
                ],
                "connected": [
                    {
                        "fmap": "Map1",
                        "fx": 4,
                        "fy": 1,
                        "tmap": "Map2",
                        "tx": 0,
                        "ty": 2
                    }
                ],
                "objects": [
                    {
                        "name": 3,
                        "x": 2,
                        "y": 4,
                        "offsetx": 0.5,
                        "offsety": 0.1378788,
                        "tilesetid": "tileobjects"
                    },
                    {
                        "name": 3,
                        "x": 4,
                        "y": 3,
                        "offsetx": 0.5490304,
                        "offsety": 0.2017402,
                        "tilesetid": "tileobjects"
                    }
                ]
            }
        ],
        "Map2": [
            {
                "height": 3,
                "width": 10,
                "tilesetid": "bottomtiles",
                "data": [
                    1,
                    1,
                    1,
                    1,
                    1,
                    1,
                    1,
                    1,
                    1,
                    1,
                    1,
                    1,
                    1,
                    1,
                    1,
                    1,
                    1,
                    1,
                    1,
                    1,
                    3,
                    3,
                    3,
                    3,
                    3,
                    3,
                    3,
                    3,
                    3,
                    3
                ],
                "walkable": [
                    1,
                    1,
                    1,
                    1,
                    1,
                    1,
                    1,
                    1,
                    1,
                    1,
                    1,
                    1,
                    1,
                    1,
                    1,
                    1,
                    1,
                    1,
                    1,
                    1,
                    0,
                    0,
                    0,
                    0,
                    0,
                    0,
                    0,
                    0,
                    0,
                    0
                ],
                "connected": [
                    {
                        "fmap": "Map2",
                        "fx": 0,
                        "fy": 2,
                        "tmap": "Map1",
                        "tx": 4,
                        "ty": 1
                    },
                    {
                        "fmap": "Map2",
                        "fx": 9,
                        "fy": 1,
                        "tmap": "Map3",
                        "tx": 0,
                        "ty": 0
                    }
                ],
                "objects": [
                    {
                        "name": 3,
                        "x": 1,
                        "y": 2,
                        "offsetx": 0.7037829,
                        "offsety": 0.2335881,
                        "tilesetid": "tileobjects"
                    },
                    {
                        "name": 3,
                        "x": 3,
                        "y": 1,
                        "offsetx": 0.4174646,
                        "offsety": 0.3328193,
                        "tilesetid": "tileobjects"
                    },
                    {
                        "name": 3,
                        "x": 7,
                        "y": 2,
                        "offsetx": 0.5549418,
                        "offsety": 0.3840504,
                        "tilesetid": "tileobjects"
                    }
                ]
            }
        ],
        "Map3": [
            {
                "height": 8,
                "width": 8,
                "tilesetid": "bottomtiles",
                "data": [
                    2,
                    2,
                    2,
                    2,
                    0,
                    0,
                    0,
                    0,
                    2,
                    2,
                    2,
                    2,
                    2,
                    0,
                    0,
                    0,
                    2,
                    2,
                    2,
                    2,
                    2,
                    1,
                    0,
                    0,
                    2,
                    2,
                    2,
                    2,
                    1,
                    1,
                    1,
                    0,
                    2,
                    2,
                    2,
                    1,
                    2,
                    2,
                    2,
                    0,
                    1,
                    1,
                    1,
                    1,
                    2,
                    2,
                    2,
                    2,
                    1,
                    1,
                    2,
                    2,
                    2,
                    2,
                    2,
                    2,
                    1,
                    1,
                    2,
                    2,
                    2,
                    2,
                    2,
                    2
                ],
                "walkable": [
                    1,
                    1,
                    1,
                    1,
                    0,
                    1,
                    0,
                    1,
                    1,
                    1,
                    1,
                    1,
                    1,
                    1,
                    1,
                    1,
                    1,
                    1,
                    1,
                    1,
                    1,
                    1,
                    1,
                    0,
                    1,
                    1,
                    1,
                    0,
                    1,
                    1,
                    1,
                    1,
                    1,
                    1,
                    1,
                    1,
                    1,
                    1,
                    1,
                    1,
                    1,
                    1,
                    1,
                    1,
                    1,
                    1,
                    1,
                    1,
                    1,
                    1,
                    1,
                    1,
                    1,
                    1,
                    1,
                    1,
                    1,
                    1,
                    1,
                    1,
                    1,
                    1,
                    1,
                    0
                ],
                "connected": [
                    {
                        "fmap": "Map3",
                        "fx": 0,
                        "fy": 0,
                        "tmap": "Map2",
                        "tx": 9,
                        "ty": 1
                    }
                ],
                "objects": [
                    {
                        "name": 2,
                        "x": 0,
                        "y": 3,
                        "offsetx": 0.7048413,
                        "offsety": 0.2906425,
                        "tilesetid": "tileobjects"
                    },
                    {
                        "name": 2,
                        "x": 1,
                        "y": 5,
                        "offsetx": 0.7305486,
                        "offsety": 0.4751289,
                        "tilesetid": "tileobjects"
                    },
                    {
                        "name": 2,
                        "x": 2,
                        "y": 0,
                        "offsetx": 0.166633,
                        "offsety": 0.2533255,
                        "tilesetid": "tileobjects"
                    },
                    {
                        "name": 0,
                        "x": 3,
                        "y": 4,
                        "offsetx": 0.4752782,
                        "offsety": 0.2740617,
                        "tilesetid": "tileobjects"
                    },
                    {
                        "name": 6,
                        "x": 4,
                        "y": 7,
                        "offsetx": 0.6248425,
                        "offsety": 0.4177698,
                        "tilesetid": "tileobjects"
                    },
                    {
                        "name": 2,
                        "x": 5,
                        "y": 1,
                        "offsetx": 0.5721895,
                        "offsety": 0.2585095,
                        "tilesetid": "tileobjects"
                    },
                    {
                        "name": 6,
                        "x": 6,
                        "y": 7,
                        "offsetx": 0.3635184,
                        "offsety": 0.2563077,
                        "tilesetid": "tileobjects"
                    },
                    {
                        "name": 1,
                        "x": 7,
                        "y": 0,
                        "offsetx": 0.4257449,
                        "offsety": 0.4492089,
                        "tilesetid": "tileobjects"
                    },
                    {
                        "name": 1,
                        "x": 7,
                        "y": 0,
                        "offsetx": 0.7304525,
                        "offsety": 0.4927385,
                        "tilesetid": "tileobjects"
                    },
                    {
                        "name": 0,
                        "x": 7,
                        "y": 0,
                        "offsetx": 0.5128067,
                        "offsety": 0.5362682,
                        "tilesetid": "tileobjects"
                    },
                    {
                        "name": 6,
                        "x": 7,
                        "y": 5,
                        "offsetx": 0.7701781,
                        "offsety": 0.3915098,
                        "tilesetid": "tileobjects"
                    }
                ]
            }
        ]
    },
    "startPos": "Map1_2_3",
    "tileSets": {
        "bottomtiles": {
            "0": "tileMagic",
            "1": "tileSand",
            "2": "tileGrass",
            "3": "tileWater",
            "4": "tileEmpty",
            "tileset": "tiles"
        },
        "tileobjects": {
            "0": "treeGreen_mid",
            "1": "treeGreen_high",
            "2": "bushGrass",
            "3": "bushSand",
            "4": "hillsGrass",
            "5": "hillsSand",
            "6": "treeMagic_mid0001",
            "tileset": "tiles"
        }
    }
}